{
  "brands": [
    {
      "name": "Admiral",
      "url": "/Admiral-Parts.htm"
    },
    {
      "name": "Frigidaire",
      "url": "/Frigidaire-Parts.htm"
    },
    {
      "name": "General Electric",
      "url": "/GE-Parts.htm"
    },
    {
      "name": "Jenn-Air",
      "url": "/Jenn-Air-Parts.htm"
    },
    {
      "name": "KitchenAid",
      "url": "/KitchenAid-Parts.htm"
    },
    {
      "name": "LG",
      "url": "/LG-Parts.htm"
    },
    {
      "name": "Maytag",
      "url": "/Maytag-Parts.htm"
    },
    {
      "name": "Whirlpool",
      "url": "/Whirlpool-Parts.htm"
    },
    {
      "name": "White-Westinghouse",
      "url": "/White-Westinghouse-Parts.htm"
    },
    {
      "name": "See all Appliance Brands",
      "url": "/Brands/"
    },
    {
      "name": "Ariens",
      "url": "/Ariens-Parts.htm"
    },
    {
      "name": "Briggs and Stratton",
      "url": "/Briggs-Stratton-Parts.htm"
    },
    {
      "name": "Echo",
      "url": "/Echo-Parts.htm"
    },
    {
      "name": "Husqvarna",
      "url": "/Husqvarna-Parts.htm"
    },
    {
      "name": "MTD",
      "url": "/MTD-Parts.htm"
    },
    {
      "name": "Murray",
      "url": "/Murray-Parts.htm"
    },
    {
      "name": "Poulan",
      "url": "/Poulan-Parts.htm"
    },
    {
      "name": "Troy-Bilt",
      "url": "/Troy-Bilt-Parts.htm"
    },
    {
      "name": "See all Lawn Equipment Brands",
      "url": "/Brands/#LawnEquipment"
    },
    {
      "name": "Dishwasher",
      "url": "/Dishwasher-Parts.htm"
    },
    {
      "name": "Dryer",
      "url": "/Dryer-Parts.htm"
    },
    {
      "name": "Stove",
      "url": "/Range-Parts.htm"
    },
    {
      "name": "Refrigerator",
      "url": "/Refrigerator-Parts.htm"
    },
    {
      "name": "Washer",
      "url": "/Washer-Parts.htm"
    },
    {
      "name": "See all Appliances",
      "url": "/Products/"
    },
    {
      "name": "Lawn Mower",
      "url": "/Lawn-Mower-Parts.htm"
    },
    {
      "name": "Snow Blower",
      "url": "/Snow-Blower-Parts.htm"
    },
    {
      "name": "Lawn Tractor",
      "url": "/Lawn-Tractor-Parts.htm"
    },
    {
      "name": "Chainsaw",
      "url": "/Chainsaw-Parts.htm"
    },
    {
      "name": "Tiller",
      "url": "/Tiller-Parts.htm"
    },
    {
      "name": "Generator",
      "url": "/Generator-Parts.htm"
    },
    {
      "name": "See all Lawn Equipment",
      "url": "/Products/#LawnEquipment"
    },
    {
      "name": "Same-day Shipping",
      "url": "/Same-Day-Shipping.htm"
    },
    {
      "name": "All Original Manufacturer Parts\n                            Genuine Quality",
      "url": "/oem/"
    },
    {
      "name": "1 Year Warranty",
      "url": "/One-Year-Warranty.htm"
    }
  ],
  "parts": [],
  "sourceUrl": "https://www.partselect.com/PS10063209-GE-RPWFE-Refrigerator-Water-Filter.htm?SourceCode=18"
}