{
  "title": "Refrigerator Ice Container",
  "partUrl": "https://www.partselect.com/PS11756280-Whirlpool-WPW10558424-Ice-Container.htm?SourceCode=18",
  "imageUrl": "data:image/gif;base64,R0lGODlhAQABAAAAACH5BAEKAAEALAAAAAABAAEAAAICTAEAOw==",
  "price": "$226.89",
  "originalPrice": "$370.09",
  "inStock": true,
  "partSelectNumber": "PS11756280",
  "manufacturerPartNumber": "WPW10558424",
  "description": "Refrigerator Ice Container PartSelect Number PS11756280 Manufacturer Part Number WPW10558424 This ice container assembly (part number WPW10558424) is for refrigerators. Ice container assembly WPW10558424 stores the ice until needed and comes with the auger that rotates to move the ice into the dispenser chute.",
  "rating": 0,
  "reviewCount": 0,
  "symptoms": [],
  "installationInstructions": {
    "author": "",
    "title": "",
    "content": ""
  },
  "readMoreLinks": {},
  "context": "refrigerator"
}