{
  "title": "Dishwasher CABLE HARNESS",
  "partUrl": "https://www.partselect.com/PS11728912-Bosch-12008383-CABLE-HARNESS.htm?SourceCode=18",
  "imageUrl": "data:image/gif;base64,R0lGODlhAQABAAAAACH5BAEKAAEALAAAAAABAAEAAAICTAEAOw==",
  "price": "$59.49",
  "originalPrice": "",
  "inStock": true,
  "partSelectNumber": "PS11728912",
  "manufacturerPartNumber": "12008383",
  "description": "Dishwasher CABLE HARNESS PartSelect Number PS11728912 Manufacturer Part Number 12008383",
  "rating": 0,
  "reviewCount": 0,
  "symptoms": [],
  "installationInstructions": {
    "author": "",
    "title": "",
    "content": ""
  },
  "readMoreLinks": {},
  "context": "dishwasher"
}