{
  "title": "Dishwasher NAMEPLATE",
  "partUrl": "https://www.partselect.com/PS11728019-Whirlpool-W10839793-NAMEPLATE.htm?SourceCode=18",
  "imageUrl": "data:image/gif;base64,R0lGODlhAQABAAAAACH5BAEKAAEALAAAAAABAAEAAAICTAEAOw==",
  "price": "$43.63",
  "originalPrice": "",
  "inStock": true,
  "partSelectNumber": "PS11728019",
  "manufacturerPartNumber": "W10839793",
  "description": "Dishwasher NAMEPLATE PartSelect Number PS11728019 Manufacturer Part Number W10839793",
  "rating": 0,
  "reviewCount": 0,
  "symptoms": [],
  "installationInstructions": {
    "author": "",
    "title": "",
    "content": ""
  },
  "readMoreLinks": {},
  "context": "dishwasher"
}