{
  "title": "Dishwasher GLASS TRAP",
  "partUrl": "https://www.partselect.com/PS12582702-GE-WD12X24663-GLASS-TRAP.htm?SourceCode=18",
  "imageUrl": "data:image/gif;base64,R0lGODlhAQABAAAAACH5BAEKAAEALAAAAAABAAEAAAICTAEAOw==",
  "price": "$10.22",
  "originalPrice": "",
  "inStock": true,
  "partSelectNumber": "PS12582702",
  "manufacturerPartNumber": "WD12X24663",
  "description": "Dishwasher GLASS TRAP PartSelect Number PS12582702 Manufacturer Part Number WD12X24663",
  "rating": 0,
  "reviewCount": 0,
  "symptoms": [],
  "installationInstructions": {
    "author": "",
    "title": "",
    "content": ""
  },
  "readMoreLinks": {},
  "context": "dishwasher"
}