{
  "title": "Dishwasher HEATING ELEMENT ASM",
  "partUrl": "https://www.partselect.com/PS12743133-GE-WD05X26780-HEATING-ELEMENT-ASM.htm?SourceCode=18",
  "imageUrl": "data:image/gif;base64,R0lGODlhAQABAAAAACH5BAEKAAEALAAAAAABAAEAAAICTAEAOw==",
  "price": "$33.05",
  "originalPrice": "",
  "inStock": true,
  "partSelectNumber": "PS12743133",
  "manufacturerPartNumber": "WD05X26780",
  "description": "Dishwasher HEATING ELEMENT ASM ★★★★★ ★★★★★ 3 Reviews PartSelect Number PS12743133 Manufacturer Part Number WD05X26780 This part is located at the bottom of the dishwasher and is not designed to heat the water that enters it. Rather, it's designed to maintain the heat of the water that enters the dishwasher.",
  "rating": 5,
  "reviewCount": 3,
  "symptoms": [
    "Not cleaning dishes properly",
    "Not drying dishes properly"
  ],
  "installationInstructions": {
    "author": "",
    "title": "",
    "content": ""
  },
  "readMoreLinks": {
    "symptoms": "https://www.partselect.com/PS12743133-GE-WD05X26780-HEATING-ELEMENT-ASM.htm?SourceCode=18#Troubleshooting"
  },
  "context": "dishwasher"
}