{
  "title": "Refrigerator Dispenser Control Module",
  "partUrl": "https://www.partselect.com/PS12071009-Frigidaire-242270106-Dispenser-Control-Module.htm?SourceCode=18",
  "imageUrl": "data:image/gif;base64,R0lGODlhAQABAAAAACH5BAEKAAEALAAAAAABAAEAAAICTAEAOw==",
  "price": "$147.60",
  "originalPrice": "$184.50",
  "inStock": true,
  "partSelectNumber": "PS12071009",
  "manufacturerPartNumber": "242270106",
  "description": "Refrigerator Dispenser Control Module ★★★★★ ★★★★★ 2 Reviews PartSelect Number PS12071009 Manufacturer Part Number 242270106 A dispenser control module is an electronic component that controls the dispensing functions within a refrigerator's door or panel. It releases filtered water, ice, and crushed ice on demand.",
  "rating": 5,
  "reviewCount": 2,
  "symptoms": [],
  "installationInstructions": {
    "author": "Gerald from MERIDIAN, MS",
    "title": "The fridge icemaker would pit out crushed ice. No whole cubes",
    "content": "I had to remove everything  inside including the surrounding box and disconnect  all the wire connector s. The   solenoid that was bad was behind the cover that the auger motor cover. . Job was  easy after  I determined I had to  remove  everything  that was not attached to the  back wall."
  },
  "readMoreLinks": {
    "instructions": "https://www.partselect.com/PS12071009-Frigidaire-242270106-Dispenser-Control-Module.htm?SourceCode=18#Instructions"
  },
  "context": "refrigerator"
}