{
  "title": "Bosch Refrigerator Water Filter",
  "partUrl": "https://www.partselect.com/PS16556076-Bosch-11034152-Refrigerator-Water-Filter.htm?SourceCode=18",
  "imageUrl": "data:image/gif;base64,R0lGODlhAQABAAAAACH5BAEKAAEALAAAAAABAAEAAAICTAEAOw==",
  "price": "$68.72",
  "originalPrice": "",
  "inStock": true,
  "partSelectNumber": "PS16556076",
  "manufacturerPartNumber": "11034152",
  "description": "Bosch Refrigerator Water Filter ★★★★★ ★★★★★ 1 Review PartSelect Number PS16556076 Manufacturer Part Number 11034152 This genuine Bosch water filter is used to help reduce contaminants in the water supply including chlorine and lead. The water filter measures approximately 2 inches in diameter and is 9 inches long. It is recommended by the manufacturer to replace the water filter every 6 months for best performance.",
  "rating": 3,
  "reviewCount": 1,
  "symptoms": [],
  "installationInstructions": {
    "author": "Louise from PLYMOUTH, MI",
    "title": "Water filter needed replacement",
    "content": "I mistakenly ordered the wrong part number online and the filter was too big.  I called Part Select and the gentleman knew the correct part number and sent it.  I also received directions for returning the incorrect part."
  },
  "readMoreLinks": {
    "instructions": "https://www.partselect.com/PS16556076-Bosch-11034152-Refrigerator-Water-Filter.htm?SourceCode=18#Instructions"
  },
  "context": "refrigerator"
}