{
  "title": "Beko Refrigerator Charging Tube",
  "partUrl": "https://www.partselect.com/PS17808084-Blomberg-4223430100-Charging-Tube.htm?SourceCode=18",
  "imageUrl": "data:image/gif;base64,R0lGODlhAQABAAAAACH5BAEKAAEALAAAAAABAAEAAAICTAEAOw==",
  "price": "$5.95",
  "originalPrice": "",
  "inStock": true,
  "partSelectNumber": "PS17808084",
  "manufacturerPartNumber": "4223430100",
  "description": "Beko Refrigerator Charging Tube PartSelect Number PS17808084 Manufacturer Part Number 4223430100",
  "rating": 0,
  "reviewCount": 0,
  "symptoms": [],
  "installationInstructions": {
    "author": "",
    "title": "",
    "content": ""
  },
  "readMoreLinks": {},
  "context": "refrigerator"
}