{
  "title": "Refrigerator Kickplate Grille - Stainless",
  "partUrl": "https://www.partselect.com/PS2363831-Frigidaire-241969405-Kickplate-Grille-Stainless.htm?SourceCode=18",
  "imageUrl": "data:image/gif;base64,R0lGODlhAQABAAAAACH5BAEKAAEALAAAAAABAAEAAAICTAEAOw==",
  "price": "$61.66",
  "originalPrice": "",
  "inStock": false,
  "partSelectNumber": "PS2363831",
  "manufacturerPartNumber": "241969405",
  "description": "Refrigerator Kickplate Grille - Stainless ★★★★★ ★★★★★ 1 Review PartSelect Number PS2363831 Manufacturer Part Number 241969405",
  "rating": 5,
  "reviewCount": 1,
  "symptoms": [],
  "installationInstructions": {
    "author": "",
    "title": "",
    "content": ""
  },
  "readMoreLinks": {},
  "context": "refrigerator"
}