{
  "title": "Refrigerator Evaporator Fan Motor Bracket",
  "partUrl": "https://www.partselect.com/PS3506290-Frigidaire-242135301-Evaporator-Fan-Motor-Bracket.htm?SourceCode=18",
  "imageUrl": "data:image/gif;base64,R0lGODlhAQABAAAAACH5BAEKAAEALAAAAAABAAEAAAICTAEAOw==",
  "price": "$8.35",
  "originalPrice": "",
  "inStock": true,
  "partSelectNumber": "PS3506290",
  "manufacturerPartNumber": "242135301",
  "description": "Refrigerator Evaporator Fan Motor Bracket PartSelect Number PS3506290 Manufacturer Part Number 242135301",
  "rating": 0,
  "reviewCount": 0,
  "symptoms": [],
  "installationInstructions": {
    "author": "Robinson Ruiz from Miami, FL",
    "title": "it doest not cool",
    "content": "after changing all the pieces the evaporator continues to freeze and stops cooling"
  },
  "readMoreLinks": {
    "instructions": "https://www.partselect.com/PS3506290-Frigidaire-242135301-Evaporator-Fan-Motor-Bracket.htm?SourceCode=18#Instructions"
  },
  "context": "refrigerator"
}