{
  "title": "RCA Refrigerator Union Connector - 5/16 Inch to 5/16 Inch",
  "partUrl": "https://www.partselect.com/PS758446-GE-WR02X11330-Union-Connector-5-16-Inch-to-5-16-Inch.htm?SourceCode=18",
  "imageUrl": "data:image/gif;base64,R0lGODlhAQABAAAAACH5BAEKAAEALAAAAAABAAEAAAICTAEAOw==",
  "price": "$9.02",
  "originalPrice": "",
  "inStock": true,
  "partSelectNumber": "PS758446",
  "manufacturerPartNumber": "WR02X11330",
  "description": "RCA Refrigerator Union Connector - 5/16 Inch to 5/16 Inch ★★★★★ ★★★★★ 10 Reviews PartSelect Number PS758446 Manufacturer Part Number WR02X11330 Quick connector for plastic water line - 5/16\" to 5/16\"",
  "rating": 4,
  "reviewCount": 10,
  "symptoms": [
    "Ice maker not making ice",
    "Leaking",
    "Not dispensing water"
  ],
  "installationInstructions": {
    "author": "Charles from Baltimore, MD",
    "title": "refrigerator",
    "content": "first i removed old gasket then pressed in new one very easy repair"
  },
  "readMoreLinks": {
    "symptoms": "https://www.partselect.com/PS758446-GE-WR02X11330-Union-Connector-5-16-Inch-to-5-16-Inch.htm?SourceCode=18#Troubleshooting",
    "instructions": "https://www.partselect.com/PS758446-GE-WR02X11330-Union-Connector-5-16-Inch-to-5-16-Inch.htm?SourceCode=18#Instructions"
  },
  "context": "refrigerator"
}