{
  "title": "Dishwasher SHELF CUP",
  "partUrl": "https://www.partselect.com/PS8756518-GE-WD28X20177-SHELF-CUP.htm?SourceCode=18",
  "imageUrl": "data:image/gif;base64,R0lGODlhAQABAAAAACH5BAEKAAEALAAAAAABAAEAAAICTAEAOw==",
  "price": "$11.20",
  "originalPrice": "",
  "inStock": false,
  "partSelectNumber": "PS8756518",
  "manufacturerPartNumber": "WD28X20177",
  "description": "Dishwasher SHELF CUP PartSelect Number PS8756518 Manufacturer Part Number WD28X20177",
  "rating": 0,
  "reviewCount": 0,
  "symptoms": [],
  "installationInstructions": {
    "author": "",
    "title": "",
    "content": ""
  },
  "readMoreLinks": {},
  "context": "dishwasher"
}