{
  "title": "General Electric Refrigerator Door Shelf Bar",
  "partUrl": "https://www.partselect.com/PS964507-GE-WR17X11889-Door-Shelf-Bar.htm?SourceCode=18",
  "imageUrl": "data:image/gif;base64,R0lGODlhAQABAAAAACH5BAEKAAEALAAAAAABAAEAAAICTAEAOw==",
  "price": "$30.10",
  "originalPrice": "",
  "inStock": true,
  "partSelectNumber": "PS964507",
  "manufacturerPartNumber": "WR17X11889",
  "description": "General Electric Refrigerator Door Shelf Bar ★★★★★ ★★★★★ 74 Reviews PartSelect Number PS964507 Manufacturer Part Number WR17X11889 This door shelf is a replacement part for your refrigerator. It is very easy to install and requires no tools. Simply pull out the existing shelf bar and snap the new one into place, making sure the locking tabs are secure.",
  "rating": 4.74,
  "reviewCount": 74,
  "symptoms": [],
  "installationInstructions": {
    "author": "allan from brighton, MI",
    "title": "broke shelf",
    "content": "easy fix... good price fast shipping, thanks"
  },
  "readMoreLinks": {
    "instructions": "https://www.partselect.com/PS964507-GE-WR17X11889-Door-Shelf-Bar.htm?SourceCode=18#Instructions"
  },
  "context": "refrigerator"
}